setup.py
pintail/__init__.py
pintail/itstool/__init__.py
pintail_itstool.egg-info/PKG-INFO
pintail_itstool.egg-info/SOURCES.txt
pintail_itstool.egg-info/dependency_links.txt
pintail_itstool.egg-info/namespace_packages.txt
pintail_itstool.egg-info/requires.txt
pintail_itstool.egg-info/top_level.txt